oa_utils/__init__.py
oa_utils/pipeline.py
oa_utils/py.typed
oa_utils-0.1.21.dist-info/LICENSE
oa_utils-0.1.21.dist-info/METADATA
oa_utils-0.1.21.dist-info/WHEEL
oa_utils-0.1.21.dist-info/RECORD
