Metadata-Version: 2.3
Name: oa-utils
Version: 0.1.21
Summary: Statically typed Python utilities for functional programming.
License: MIT
Keywords: utilities,functional programming,fluent interface,collection pipeline
Author: Oleg Alexander
Requires-Python: >=3.10
Classifier: License :: OSI Approved :: MIT License
Classifier: Programming Language :: Python :: 3
Classifier: Programming Language :: Python :: 3.10
Classifier: Programming Language :: Python :: 3.11
Classifier: Programming Language :: Python :: 3.12
Classifier: Programming Language :: Python :: 3.13
Requires-Dist: more-itertools (>=10.7.0,<11.0.0)
Requires-Dist: tabulate (>=0.9.0,<0.10.0)
Project-URL: Homepage, https://github.com/OlegAlexander/oa-utils
